ancypwn-terminal-alacritty/__init__.py
ancypwn-terminal-alacritty/alacritty.py
ancypwn_terminal_alacritty/__init__.py
ancypwn_terminal_alacritty/alacritty.py
ancypwn_terminal_alacritty-0.0.1.dist-info/METADATA
ancypwn_terminal_alacritty-0.0.1.dist-info/WHEEL
ancypwn_terminal_alacritty-0.0.1.dist-info/top_level.txt
ancypwn_terminal_alacritty-0.0.1.dist-info/RECORD
