Metadata-Version: 2.1
Name: ancypwn-terminal-alacritty
Version: 0.0.1
Summary: ancypwn terminal plugin
Home-page: https://github.com/Escapingbug/ancypwn-terminal-alacritty
Author: Anciety
Author-email: ancypwn@pku.edu.cn
License: UNKNOWN
Platform: UNKNOWN
